CHANGELOG.rst
LICENSE
MANIFEST.in
README.rst
setup.py
djangoappengine/__init__.py
djangoappengine/boot.py
djangoappengine/dbindexes.py
djangoappengine/mail.py
djangoappengine/models.py
djangoappengine/settings_base.py
djangoappengine/storage.py
djangoappengine/utils.py
djangoappengine/views.py
djangoappengine.egg-info/PKG-INFO
djangoappengine.egg-info/SOURCES.txt
djangoappengine.egg-info/dependency_links.txt
djangoappengine.egg-info/not-zip-safe
djangoappengine.egg-info/requires.txt
djangoappengine.egg-info/top_level.txt
djangoappengine/appstats/__init__.py
djangoappengine/appstats/ui.py
djangoappengine/conf/project_template/app.yaml
djangoappengine/conf/project_template/cron.yaml
djangoappengine/conf/project_template/index.yaml
djangoappengine/conf/project_template/indexes.py
djangoappengine/conf/project_template/manage.py
djangoappengine/conf/project_template/settings.py
djangoappengine/conf/project_template/project_name/__init__.py
djangoappengine/conf/project_template/project_name/settings.py
djangoappengine/conf/project_template/project_name/urls.py
djangoappengine/db/__init__.py
djangoappengine/db/base.py
djangoappengine/db/compiler.py
djangoappengine/db/creation.py
djangoappengine/db/db_settings.py
djangoappengine/db/expressions.py
djangoappengine/db/stubs.py
djangoappengine/db/utils.py
djangoappengine/deferred/__init__.py
djangoappengine/deferred/handler.py
djangoappengine/lib/__init__.py
djangoappengine/lib/memcache.py
djangoappengine/main/__init__.py
djangoappengine/main/main.py
djangoappengine/management/__init__.py
djangoappengine/management/commands/__init__.py
djangoappengine/management/commands/deploy.py
djangoappengine/management/commands/remote.py
djangoappengine/management/commands/runserver.py
djangoappengine/management/commands/testserver.py
djangoappengine/mapreduce/__init__.py
djangoappengine/mapreduce/handler.py
djangoappengine/mapreduce/input_readers.py
djangoappengine/mapreduce/pipeline.py
djangoappengine/tests/__init__.py
djangoappengine/tests/models.py
djangoappengine/tests/test_backend.py
djangoappengine/tests/test_field_db_conversion.py
djangoappengine/tests/test_field_options.py
djangoappengine/tests/test_filter.py
djangoappengine/tests/test_keys.py
